llmstatemachine/__init__.py
llmstatemachine/function.py
llmstatemachine/workflow_agent.py
llmstatemachine-0.7.0.dist-info/LICENSE
llmstatemachine-0.7.0.dist-info/METADATA
llmstatemachine-0.7.0.dist-info/WHEEL
llmstatemachine-0.7.0.dist-info/RECORD
