Metadata-Version: 2.1
Name: llmstatemachine
Version: 0.7.0
Summary: A Python library for building GPT-powered agents with state machine logic and chat history memory.
Author: Mikko Korpela
Author-email: mikko@robocorp.com
Requires-Python: >=3.10,<4.0
Classifier: Programming Language :: Python :: 3
Classifier: Programming Language :: Python :: 3.10
Classifier: Programming Language :: Python :: 3.11
Classifier: Programming Language :: Python :: 3.12
Requires-Dist: openai (>=1.3.3,<2.0.0)
